lxcommon
