Metadata-Version: 1.0
Name: lxcommon
Version: 2.12.0
Summary: LX-Common is a package for code bits shared across several LX tools.
Home-page: UNKNOWN
Author: Luís Gomes
Author-email: luis.gomes@di.fc.ul.pt
License: UNKNOWN
Platform: UNKNOWN
